{"cameraMode":{"drawMode":0,"name":"Shaded","section":"Shading Mode"},"sceneLighting":false,"audioPlay":false,"sceneViewState":{"m_AlwaysRefresh":false,"showFog":true,"showSkybox":true,"showFlares":true,"showImageEffects":true,"showParticleSystems":true,"showVisualEffectGraphs":true,"m_FxEnabled":true},"in2DMode":false,"pivot":{"x":1.5832295417785645,"y":9.814308166503907,"z":-3.7381255626678469},"rotation":{"x":0.07787866145372391,"y":-0.7540174126625061,"z":0.0909179300069809,"w":0.6458646655082703},"size":2.084376573562622,"orthographic":false}